[
  {
    "time": "2025-11-09 18:00 IST",
    "game": "football",
    "league": "",
    "home_team": "بلجيكا تحت 17",
    "away_team": "تونس تحت 17",
    "label": "بلج-تون",
    "Logo": "https://pub-9099b5bec5c7424e97829a0fd8a31977.r2.dev/cdn/2025/11/5243.png",
    "url": "https://pl.yallashooot.video/albaplayer/ch1/"
  },
  {
    "time": "2025-11-09 18:15 IST",
    "game": "football",
    "league": "",
    "home_team": "سيراميكا كليوباترا",
    "away_team": "بيراميدز",
    "label": "سير-بير",
    "Logo": "https://pub-9099b5bec5c7424e97829a0fd8a31977.r2.dev/cdn/2025/11/50882.png",
    "url": "https://pl.yallashooot.video/albaplayer/dubai-sports-1/"
  },
  {
    "time": "2025-11-09 18:30 IST",
    "game": "football",
    "league": "",
    "home_team": "أتلتيك بلباو",
    "away_team": "ريال أوفييدو",
    "label": "أتل-ريا",
    "Logo": "https://pub-9099b5bec5c7424e97829a0fd8a31977.r2.dev/cdn/2025/10/144.png",
    "url": "https://pl.yallashooot.video/albaplayer/bein1/"
  },
  {
    "time": "2025-11-09 19:00 IST",
    "game": "football",
    "league": "",
    "home_team": "المغرب تحت 17",
    "away_team": "كاليدونيا الجديدة تحت 17",
    "label": "الم-كال",
    "Logo": "https://pub-9099b5bec5c7424e97829a0fd8a31977.r2.dev/cdn/2025/11/2320.png",
    "url": "https://pl.yallashooot.video/albaplayer/ch2/"
  },
  {
    "time": "2025-11-09 19:00 IST",
    "game": "football",
    "league": "",
    "home_team": "النادي الأفريقي",
    "away_team": "الترجي",
    "label": "الن-الت",
    "Logo": "https://pub-9099b5bec5c7424e97829a0fd8a31977.r2.dev/cdn/2025/10/8239.png",
    "url": "https://pl.yallashooot.video/albaplayer/el-watania-1/"
  },
  {
    "time": "2025-11-09 19:30 IST",
    "game": "football",
    "league": "",
    "home_team": "نوتنجهام فورست",
    "away_team": "ليدز يونايتد",
    "label": "نوت-ليد",
    "Logo": "https://pub-9099b5bec5c7424e97829a0fd8a31977.r2.dev/cdn/2025/10/29.png",
    "url": "https://pl.yallashooot.video/albaplayer/bein6/"
  },
  {
    "time": "2025-11-09 19:30 IST",
    "game": "football",
    "league": "",
    "home_team": "بولونيا",
    "away_team": "نابولي",
    "label": "بول-ناب",
    "Logo": "https://pub-9099b5bec5c7424e97829a0fd8a31977.r2.dev/cdn/2025/10/245.png",
    "url": "https://pl.yallashooot.video/albaplayer/ad-premium-1/"
  },
  {
    "time": "2025-11-09 19:30 IST",
    "game": "football",
    "league": "",
    "home_team": "كريستال بالاس",
    "away_team": "برايتون",
    "label": "كري-برا",
    "Logo": "https://pub-9099b5bec5c7424e97829a0fd8a31977.r2.dev/cdn/2025/10/10.png",
    "url": "https://pl.yallashooot.video/albaplayer/bein3/"
  },
  {
    "time": "2025-11-09 19:30 IST",
    "game": "football",
    "league": "",
    "home_team": "برينتفورد",
    "away_team": "نيوكاسل يونايتد",
    "label": "بري-نيو",
    "Logo": "https://pub-9099b5bec5c7424e97829a0fd8a31977.r2.dev/cdn/2025/10/63.png",
    "url": "https://pl.yallashooot.video/albaplayer/bein4/"
  },
  {
    "time": "2025-11-09 19:30 IST",
    "game": "football",
    "league": "",
    "home_team": "أستون فيلا",
    "away_team": "بورنموث",
    "label": "أست-بور",
    "Logo": "https://pub-9099b5bec5c7424e97829a0fd8a31977.r2.dev/cdn/2025/10/109.png",
    "url": "https://pl.yallashooot.video/albaplayer/bein5/"
  },
  {
    "time": "2025-11-09 20:15 IST",
    "game": "football",
    "league": "",
    "home_team": "الإمارات تحت 17",
    "away_team": "السنغال تحت 17",
    "label": "الإ-الس",
    "Logo": "https://pub-9099b5bec5c7424e97829a0fd8a31977.r2.dev/cdn/2025/11/5295.png",
    "url": "https://pl.yallashooot.video/albaplayer//"
  },
  {
    "time": "2025-11-09 20:30 IST",
    "game": "football",
    "league": "",
    "home_team": "أولمبيك آسفي",
    "away_team": "الوداد الرياضي",
    "label": "أول-الو",
    "Logo": "https://pub-9099b5bec5c7424e97829a0fd8a31977.r2.dev/cdn/2025/10/8210.png",
    "url": "https://pl.yallashooot.video/albaplayer/arryadia/"
  },
  {
    "time": "2025-11-09 20:45 IST",
    "game": "football",
    "league": "",
    "home_team": "رايو فاييكانو",
    "away_team": "ريال مدريد",
    "label": "راي-ريا",
    "Logo": "https://pub-9099b5bec5c7424e97829a0fd8a31977.r2.dev/cdn/2025/10/174.png",
    "url": "https://pl.yallashooot.video/albaplayer//"
  },
  {
    "time": "2025-11-09 21:00 IST",
    "game": "football",
    "league": "",
    "home_team": "الأهلي",
    "away_team": "الزمالك",
    "label": "الأ-الز",
    "Logo": "https://pub-9099b5bec5c7424e97829a0fd8a31977.r2.dev/cdn/2025/10/7085.png",
    "url": "https://pl.yallashooot.video/albaplayer/dubai-sports-1/"
  },
  {
    "time": "2025-11-09 21:15 IST",
    "game": "football",
    "league": "",
    "home_team": "بوليفيا تحت 17",
    "away_team": "قطر تحت 17",
    "label": "بول-قطر",
    "Logo": "https://pub-9099b5bec5c7424e97829a0fd8a31977.r2.dev/cdn/2025/11/5278.png",
    "url": "https://pl.yallashooot.video/albaplayer/al-kass-4/"
  },
  {
    "time": "2025-11-09 21:45 IST",
    "game": "football",
    "league": "",
    "home_team": "ستراسبورج",
    "away_team": "ليل",
    "label": "ستر-ليل",
    "Logo": "https://pub-9099b5bec5c7424e97829a0fd8a31977.r2.dev/cdn/2025/10/479.png",
    "url": "https://pl.yallashooot.video/albaplayer//"
  },
  {
    "time": "2025-11-09 22:00 IST",
    "game": "football",
    "league": "",
    "home_team": "مانشستر سيتي",
    "away_team": "ليفربول",
    "label": "مان-ليف",
    "Logo": "https://pub-9099b5bec5c7424e97829a0fd8a31977.r2.dev/cdn/2025/10/110.png",
    "url": "https://pl.yallashooot.video/albaplayer//"
  },
  {
    "time": "2025-11-09 22:30 IST",
    "game": "football",
    "league": "",
    "home_team": "روما",
    "away_team": "أودينيزي",
    "label": "روم-أود",
    "Logo": "https://pub-9099b5bec5c7424e97829a0fd8a31977.r2.dev/cdn/2025/10/225.png",
    "url": "https://pl.yallashooot.video/albaplayer//"
  },
  {
    "time": "2025-11-09 22:30 IST",
    "game": "football",
    "league": "",
    "home_team": "اتحاد طنجة",
    "away_team": "نهضة بركان",
    "label": "اتح-نهض",
    "Logo": "https://pub-9099b5bec5c7424e97829a0fd8a31977.r2.dev/cdn/2025/10/14596.png",
    "url": "https://pl.yallashooot.video/albaplayer//"
  },
  {
    "time": "2025-11-09 23:00 IST",
    "game": "football",
    "league": "",
    "home_team": "فالنسيا",
    "away_team": "ريال بيتيس",
    "label": "فال-ريا",
    "Logo": "https://pub-9099b5bec5c7424e97829a0fd8a31977.r2.dev/cdn/2025/10/139.png",
    "url": "https://pl.yallashooot.video/albaplayer//"
  },
  {
    "time": "2025-11-09 23:00 IST",
    "game": "football",
    "league": "",
    "home_team": "ريال مايوركا",
    "away_team": "خيتافي",
    "label": "ريا-خيت",
    "Logo": "https://pub-9099b5bec5c7424e97829a0fd8a31977.r2.dev/cdn/2025/10/142.png",
    "url": "https://pl.yallashooot.video/albaplayer//"
  },
  {
    "time": "2025-11-10 00:30 IST",
    "game": "football",
    "league": "",
    "home_team": "الجيش الملكي",
    "away_team": "المغرب الفاسي",
    "label": "الج-الم",
    "Logo": "https://pub-9099b5bec5c7424e97829a0fd8a31977.r2.dev/cdn/2025/10/5455.png",
    "url": "https://pl.yallashooot.video/albaplayer//"
  },
  {
    "time": "2025-11-10 01:15 IST",
    "game": "football",
    "league": "",
    "home_team": "أولمبيك ليون",
    "away_team": "باريس سان جيرمان",
    "label": "أول-بار",
    "Logo": "https://pub-9099b5bec5c7424e97829a0fd8a31977.r2.dev/cdn/2025/10/465.png",
    "url": "https://pl.yallashooot.video/albaplayer//"
  },
  {
    "time": "2025-11-10 01:15 IST",
    "game": "football",
    "league": "",
    "home_team": "إنتر ميلان",
    "away_team": "لاتسيو",
    "label": "إنت-لات",
    "Logo": "https://pub-9099b5bec5c7424e97829a0fd8a31977.r2.dev/cdn/2025/09/224-1.png",
    "url": "https://pl.yallashooot.video/albaplayer//"
  },
  {
    "time": "2025-11-10 01:30 IST",
    "game": "football",
    "league": "",
    "home_team": "سيلتا فيجو",
    "away_team": "برشلونة",
    "label": "سيل-برش",
    "Logo": "https://pub-9099b5bec5c7424e97829a0fd8a31977.r2.dev/cdn/2025/10/158.png",
    "url": "https://pl.yallashooot.video/albaplayer//"
  },
  {
    "time": "2025-11-09 17:00 IST",
    "game": "football",
    "league": "",
    "home_team": "أتالانتا",
    "away_team": "ساسولو",
    "label": "أتا-ساس",
    "Logo": "https://pub-9099b5bec5c7424e97829a0fd8a31977.r2.dev/cdn/2025/09/232-1.png",
    "url": "https://pl.yallashooot.video/albaplayer/ad-premium-1/"
  }
]