[
  {
    "time": "2026-04-08 22:30 IST",
    "game": "football",
    "league": "",
    "home_team": "Al Damac",
    "away_team": "Al Qadsiah",
    "label": "ald-alq",
    "home_logo": "https://crests.football-data.org/57.png",
    "away_logo": "https://crests.football-data.org/57.png",
    "url": "https://ww1.sportszonline.click/channels/pt/sporttv1.php"
  },
  {
    "time": "2026-04-08 23:15 IST",
    "game": "football",
    "league": "",
    "home_team": "Rayo Vallecano",
    "away_team": "AEK Athens",
    "label": "ray-aek",
    "home_logo": "https://crests.football-data.org/87.png",
    "away_logo": "https://raw.githubusercontent.com/gowrapavan/Goal4u/main/public/assets/img/tv-logo/benfica.png",
    "url": "https://ww1.sportszonline.click/channels/hd/hd5.php"
  },
  {
    "time": "2026-04-08 23:15 IST",
    "game": "football",
    "league": "",
    "home_team": "Rayo Vallecano",
    "away_team": "AEK Athens",
    "label": "ray-aek",
    "home_logo": "https://crests.football-data.org/87.png",
    "away_logo": "https://raw.githubusercontent.com/gowrapavan/Goal4u/main/public/assets/img/tv-logo/fcboavista.png",
    "url": "https://ww1.sportszonline.click/channels/hd/hd6.php"
  },
  {
    "time": "2026-04-08 23:15 IST",
    "game": "football",
    "league": "",
    "home_team": "Rayo Vallecano",
    "away_team": "AEK Athens",
    "label": "ray-aek",
    "home_logo": "https://crests.football-data.org/87.png",
    "away_logo": "https://raw.githubusercontent.com/gowrapavan/Goal4u/main/public/assets/img/tv-logo/valencia.png",
    "url": "https://ww1.sportszonline.click/channels/hd/hd11.php"
  },
  {
    "time": "2026-04-08 23:15 IST",
    "game": "football",
    "league": "",
    "home_team": "Rayo Vallecano",
    "away_team": "AEK Athens",
    "label": "ray-aek",
    "home_logo": "https://crests.football-data.org/87.png",
    "away_logo": "https://raw.githubusercontent.com/gowrapavan/Goal4u/main/public/assets/img/tv-logo/porto.png",
    "url": "https://ww1.sportszonline.click/channels/pt/eleven1.php"
  },
  {
    "time": "2026-04-09 01:15 IST",
    "game": "football",
    "league": "",
    "home_team": "Handball: Paris Saint Germain",
    "away_team": "One Veszprém",
    "label": "han-one",
    "home_logo": "https://raw.githubusercontent.com/gowrapavan/Goal4u/main/public/assets/img/tv-logo/braga.png",
    "away_logo": "https://crests.football-data.org/457.png",
    "url": "https://ww1.sportszonline.click/channels/pt/sporttv4.php"
  },
  {
    "time": "2026-04-09 01:30 IST",
    "game": "football",
    "league": "",
    "home_team": "Freiburg",
    "away_team": "Celta de Vigo",
    "label": "fre-cel",
    "home_logo": "https://crests.football-data.org/17.png",
    "away_logo": "https://crests.football-data.org/558.png",
    "url": "https://ww1.sportszonline.click/channels/hd/hd5.php"
  },
  {
    "time": "2026-04-09 01:30 IST",
    "game": "football",
    "league": "",
    "home_team": "Freiburg",
    "away_team": "Celta de Vigo",
    "label": "fre-cel",
    "home_logo": "https://crests.football-data.org/17.png",
    "away_logo": "https://crests.football-data.org/558.png",
    "url": "https://ww1.sportszonline.click/channels/hd/hd6.php"
  },
  {
    "time": "2026-04-09 01:30 IST",
    "game": "football",
    "league": "",
    "home_team": "Freiburg",
    "away_team": "Celta de Vigo",
    "label": "fre-cel",
    "home_logo": "https://crests.football-data.org/17.png",
    "away_logo": "https://crests.football-data.org/558.png",
    "url": "https://ww1.sportszonline.click/channels/hd/hd3.php"
  },
  {
    "time": "2026-04-09 01:30 IST",
    "game": "football",
    "league": "",
    "home_team": "Freiburg",
    "away_team": "Celta de Vigo",
    "label": "fre-cel",
    "home_logo": "https://crests.football-data.org/17.png",
    "away_logo": "https://crests.football-data.org/558.png",
    "url": "https://ww1.sportszonline.click/channels/pt/eleven2.php"
  },
  {
    "time": "2026-04-09 01:30 IST",
    "game": "football",
    "league": "",
    "home_team": "Bologna",
    "away_team": "Aston Villa",
    "label": "bol-ast",
    "home_logo": "https://crests.football-data.org/103.png",
    "away_logo": "https://crests.football-data.org/58.png",
    "url": "https://ww1.sportszonline.click/channels/hd/hd2.php"
  },
  {
    "time": "2026-04-09 01:30 IST",
    "game": "football",
    "league": "",
    "home_team": "Bologna",
    "away_team": "Aston Villa",
    "label": "bol-ast",
    "home_logo": "https://crests.football-data.org/103.png",
    "away_logo": "https://crests.football-data.org/58.png",
    "url": "https://ww1.sportszonline.click/channels/hd/hd7.php"
  },
  {
    "time": "2026-04-09 01:30 IST",
    "game": "football",
    "league": "",
    "home_team": "Bologna",
    "away_team": "Aston Villa",
    "label": "bol-ast",
    "home_logo": "https://crests.football-data.org/103.png",
    "away_logo": "https://crests.football-data.org/58.png",
    "url": "https://ww1.sportszonline.click/channels/pt/eleven1.php"
  },
  {
    "time": "2026-04-09 01:30 IST",
    "game": "football",
    "league": "",
    "home_team": "Porto",
    "away_team": "Nottingham Forest",
    "label": "por-not",
    "home_logo": "https://raw.githubusercontent.com/gowrapavan/Goal4u/main/public/assets/img/tv-logo/porto.png",
    "away_logo": "https://crests.football-data.org/351.png",
    "url": "https://ww1.sportszonline.click/channels/hd/hd1.php"
  },
  {
    "time": "2026-04-09 01:30 IST",
    "game": "football",
    "league": "",
    "home_team": "Porto",
    "away_team": "Nottingham Forest",
    "label": "por-not",
    "home_logo": "https://raw.githubusercontent.com/gowrapavan/Goal4u/main/public/assets/img/tv-logo/valencia.png",
    "away_logo": "https://crests.football-data.org/351.png",
    "url": "https://ww1.sportszonline.click/channels/pt/sporttv5.php"
  },
  {
    "time": "2026-04-09 01:30 IST",
    "game": "football",
    "league": "",
    "home_team": "Shakhtar Donetsk",
    "away_team": "AZ",
    "label": "sha-az",
    "home_logo": "https://raw.githubusercontent.com/gowrapavan/Goal4u/main/public/assets/img/tv-logo/valencia.png",
    "away_logo": "https://crests.football-data.org/108.png",
    "url": "https://ww1.sportszonline.click/channels/hd/hd11.php"
  },
  {
    "time": "2026-04-09 01:30 IST",
    "game": "football",
    "league": "",
    "home_team": "Mainz 05",
    "away_team": "Strasbourg",
    "label": "mai-str",
    "home_logo": "https://crests.football-data.org/15.png",
    "away_logo": "https://crests.football-data.org/576.png",
    "url": "https://ww1.sportszonline.click/channels/hd/hd4.php"
  },
  {
    "time": "2026-04-09 01:30 IST",
    "game": "football",
    "league": "",
    "home_team": "Mainz 05",
    "away_team": "Strasbourg",
    "label": "mai-str",
    "home_logo": "https://crests.football-data.org/15.png",
    "away_logo": "https://crests.football-data.org/576.png",
    "url": "https://ww1.sportszonline.click/channels/hd/hd10.php"
  },
  {
    "time": "2026-04-09 01:30 IST",
    "game": "football",
    "league": "",
    "home_team": "Crystal Palace",
    "away_team": "Fiorentina",
    "label": "cry-fio",
    "home_logo": "https://crests.football-data.org/354.png",
    "away_logo": "https://crests.football-data.org/99.png",
    "url": "https://ww1.sportszonline.click/channels/hd/hd9.php"
  },
  {
    "time": "2026-04-09 01:30 IST",
    "game": "football",
    "league": "",
    "home_team": "Crystal Palace",
    "away_team": "Fiorentina",
    "label": "cry-fio",
    "home_logo": "https://crests.football-data.org/354.png",
    "away_logo": "https://crests.football-data.org/99.png",
    "url": "https://ww1.sportszonline.click/channels/hd/hd8.php"
  },
  {
    "time": "2026-04-09 01:30 IST",
    "game": "football",
    "league": "",
    "home_team": "Crystal Palace",
    "away_team": "Fiorentina",
    "label": "cry-fio",
    "home_logo": "https://crests.football-data.org/354.png",
    "away_logo": "https://crests.football-data.org/99.png",
    "url": "https://ww1.sportszonline.click/channels/pt/eleven3.php"
  },
  {
    "time": "2026-04-09 04:30 IST",
    "game": "football",
    "league": "",
    "home_team": "Rosario Central",
    "away_team": "Independiente del Valle",
    "label": "ros-ind",
    "home_logo": "https://raw.githubusercontent.com/gowrapavan/Goal4u/main/public/assets/img/tv-logo/maritimo.png",
    "away_logo": "https://raw.githubusercontent.com/gowrapavan/Goal4u/main/public/assets/img/tv-logo/benfica.png",
    "url": "https://ww1.sportszonline.click/channels/hd/hd10.php"
  },
  {
    "time": "2026-04-09 04:30 IST",
    "game": "football",
    "league": "",
    "home_team": "Rosario Central",
    "away_team": "Independiente del Valle",
    "label": "ros-ind",
    "home_logo": "https://raw.githubusercontent.com/gowrapavan/Goal4u/main/public/assets/img/tv-logo/maritimo.png",
    "away_logo": "https://raw.githubusercontent.com/gowrapavan/Goal4u/main/public/assets/img/tv-logo/maritimo.png",
    "url": "https://ww1.sportszonline.click/channels/hd/hd8.php"
  },
  {
    "time": "2026-04-09 04:30 IST",
    "game": "football",
    "league": "",
    "home_team": "Rosario Central",
    "away_team": "Independiente del Valle",
    "label": "ros-ind",
    "home_logo": "https://raw.githubusercontent.com/gowrapavan/Goal4u/main/public/assets/img/tv-logo/aves.png",
    "away_logo": "https://raw.githubusercontent.com/gowrapavan/Goal4u/main/public/assets/img/tv-logo/fcboavista.png",
    "url": "https://ww1.sportszonline.click/channels/pt/sporttv1.php"
  },
  {
    "time": "2026-04-09 04:30 IST",
    "game": "football",
    "league": "",
    "home_team": "Rosario Central",
    "away_team": "Independiente del Valle",
    "label": "ros-ind",
    "home_logo": "https://raw.githubusercontent.com/gowrapavan/Goal4u/main/public/assets/img/tv-logo/maritimo.png",
    "away_logo": "https://raw.githubusercontent.com/gowrapavan/Goal4u/main/public/assets/img/tv-logo/maritimo.png",
    "url": "https://ww1.sportszonline.click/channels/bra/br6.php"
  },
  {
    "time": "2026-04-09 04:30 IST",
    "game": "football",
    "league": "",
    "home_team": "Botafogo",
    "away_team": "Caracas",
    "label": "bot-car",
    "home_logo": "https://raw.githubusercontent.com/gowrapavan/Goal4u/main/public/assets/img/tv-logo/fcboavista.png",
    "away_logo": "https://raw.githubusercontent.com/gowrapavan/Goal4u/main/public/assets/img/tv-logo/braga.png",
    "url": "https://ww1.sportszonline.click/channels/pt/sporttv2.php"
  },
  {
    "time": "2026-04-09 04:30 IST",
    "game": "football",
    "league": "",
    "home_team": "Botafogo",
    "away_team": "Caracas",
    "label": "bot-car",
    "home_logo": "https://raw.githubusercontent.com/gowrapavan/Goal4u/main/public/assets/img/tv-logo/porto.png",
    "away_logo": "https://raw.githubusercontent.com/gowrapavan/Goal4u/main/public/assets/img/tv-logo/valencia.png",
    "url": "https://ww1.sportszonline.click/channels/bra/br2.php"
  },
  {
    "time": "2026-04-08 06:30 IST",
    "game": "football",
    "league": "",
    "home_team": "Platense",
    "away_team": "Corinthians",
    "label": "pla-cor",
    "home_logo": "https://raw.githubusercontent.com/gowrapavan/Goal4u/main/public/assets/img/tv-logo/sporting.png",
    "away_logo": "https://raw.githubusercontent.com/gowrapavan/Goal4u/main/public/assets/img/tv-logo/maritimo.png",
    "url": "https://ww1.sportszonline.click/channels/pt/sporttv1.php"
  },
  {
    "time": "2026-04-08 07:00 IST",
    "game": "football",
    "league": "",
    "home_team": "Macará",
    "away_team": "América de Cali",
    "label": "mac-amr",
    "home_logo": "https://raw.githubusercontent.com/gowrapavan/Goal4u/main/public/assets/img/tv-logo/maritimo.png",
    "away_logo": "https://raw.githubusercontent.com/gowrapavan/Goal4u/main/public/assets/img/tv-logo/benfica.png",
    "url": "https://ww1.sportszonline.click/channels/hd/hd10.php"
  },
  {
    "time": "2026-04-08 06:30 IST",
    "game": "football",
    "league": "",
    "home_team": "Platense",
    "away_team": "Corinthians",
    "label": "pla-cor",
    "home_logo": "https://raw.githubusercontent.com/gowrapavan/Goal4u/main/public/assets/img/tv-logo/valencia.png",
    "away_logo": "https://raw.githubusercontent.com/gowrapavan/Goal4u/main/public/assets/img/tv-logo/fcboavista.png",
    "url": "https://ww1.sportszonline.click/channels/bra/br1.php"
  },
  {
    "time": "2026-04-08 07:00 IST",
    "game": "football",
    "league": "",
    "home_team": "Macará",
    "away_team": "América de Cali",
    "label": "mac-amr",
    "home_logo": "https://raw.githubusercontent.com/gowrapavan/Goal4u/main/public/assets/img/tv-logo/sporting.png",
    "away_logo": "https://raw.githubusercontent.com/gowrapavan/Goal4u/main/public/assets/img/tv-logo/valencia.png",
    "url": "https://ww1.sportszonline.click/channels/hd/hd8.php"
  },
  {
    "time": "2026-04-08 07:00 IST",
    "game": "football",
    "league": "",
    "home_team": "Carabobo",
    "away_team": "RB Bragantino",
    "label": "car-rbb",
    "home_logo": "https://raw.githubusercontent.com/gowrapavan/Goal4u/main/public/assets/img/tv-logo/valencia.png",
    "away_logo": "https://crests.football-data.org/721.png",
    "url": "https://ww1.sportszonline.click/channels/bra/br6.php"
  },
  {
    "time": "2026-04-08 08:30 IST",
    "game": "football",
    "league": "",
    "home_team": "Santa Fe",
    "away_team": "Peñarol",
    "label": "san-pea",
    "home_logo": "https://raw.githubusercontent.com/gowrapavan/Goal4u/main/public/assets/img/tv-logo/porto.png",
    "away_logo": "https://raw.githubusercontent.com/gowrapavan/Goal4u/main/public/assets/img/tv-logo/benfica.png",
    "url": "https://ww1.sportszonline.click/channels/hd/hd10.php"
  },
  {
    "time": "2026-04-08 08:30 IST",
    "game": "football",
    "league": "",
    "home_team": "Santa Fe",
    "away_team": "Peñarol",
    "label": "san-pea",
    "home_logo": "https://raw.githubusercontent.com/gowrapavan/Goal4u/main/public/assets/img/tv-logo/braga.png",
    "away_logo": "https://raw.githubusercontent.com/gowrapavan/Goal4u/main/public/assets/img/tv-logo/valencia.png",
    "url": "https://ww1.sportszonline.click/channels/hd/hd8.php"
  }
]